odoo8_addon_admin_technical_features-8.0.0.1.0-py2.7-nspkg.pth
odoo_addons/admin_technical_features/res_groups.xml
odoo_addons/admin_technical_features/__openerp__.py
odoo_addons/admin_technical_features/__init__.py
odoo_addons/admin_technical_features/README.rst
odoo_addons/admin_technical_features/static/admin_technical_features.png
odoo_addons/admin_technical_features/static/description/icon.png
odoo8_addon_admin_technical_features-8.0.0.1.0.dist-info/top_level.txt
odoo8_addon_admin_technical_features-8.0.0.1.0.dist-info/WHEEL
odoo8_addon_admin_technical_features-8.0.0.1.0.dist-info/RECORD
odoo8_addon_admin_technical_features-8.0.0.1.0.dist-info/metadata.json
odoo8_addon_admin_technical_features-8.0.0.1.0.dist-info/DESCRIPTION.rst
odoo8_addon_admin_technical_features-8.0.0.1.0.dist-info/METADATA
odoo8_addon_admin_technical_features-8.0.0.1.0.dist-info/namespace_packages.txt
